aionefit/__init__.py
aionefit/provider/__init__.py
aionefit/provider/pyaes_impl.py
aionefit/provider/slixmpp_impl.py
aionefit-0.3.dist-info/METADATA
aionefit-0.3.dist-info/WHEEL
aionefit-0.3.dist-info/top_level.txt
aionefit-0.3.dist-info/RECORD
