Metadata-Version: 2.1
Name: aionefit
Version: 0.3
Summary: asyncio library for Bosch thermostats
Home-page: https://github.com/marconfus/aionefit
Author: Marco Reichwald
Author-email: marconfus@gmail.com
License: MIT
Platform: UNKNOWN
Classifier: License :: OSI Approved :: MIT License
Classifier: Programming Language :: Python
Classifier: Programming Language :: Python :: 3
Classifier: Programming Language :: Python :: 3.6
Classifier: Programming Language :: Python :: Implementation :: CPython
Classifier: Programming Language :: Python :: Implementation :: PyPy
Requires-Python: >=3.5.0
Requires-Dist: slixmpp
Requires-Dist: pyaes
